phone_modem/__init__.py
phone_modem/exceptions.py
phone_modem-0.1.2.dist-info/LICENSE
phone_modem-0.1.2.dist-info/METADATA
phone_modem-0.1.2.dist-info/WHEEL
phone_modem-0.1.2.dist-info/top_level.txt
phone_modem-0.1.2.dist-info/RECORD
